flufl/i18n/__init__.py
flufl/i18n/_application.py
flufl/i18n/_expand.py
flufl/i18n/_registry.py
flufl/i18n/_strategy.py
flufl/i18n/_substitute.py
flufl/i18n/_translator.py
flufl/i18n/py.typed
flufl/i18n/types.py
flufl_i18n-5.2.0.dist-info/METADATA
flufl_i18n-5.2.0.dist-info/WHEEL
flufl_i18n-5.2.0.dist-info/licenses/LICENSE
flufl_i18n-5.2.0.dist-info/RECORD
