Metadata-Version: 2.4
Name: flufl.i18n
Version: 5.2.0
Summary: A high level API for internationalizing Python libraries and applications
Project-URL: Home Page, https://flufli18n.readthedocs.io
Project-URL: Documentation, https://flufli18n.readthedocs.io
Project-URL: Source Code, https://gitlab.com/warsaw/flufl.i18n.git
Project-URL: Bug Tracker, https://gitlab.com/warsaw/flufl.i18n/issues
Author-email: Barry Warsaw <barry@python.org>
License: Apache-2.0
License-File: LICENSE
Keywords: i18n,internationalization
Classifier: Development Status :: 5 - Production/Stable
Classifier: Development Status :: 6 - Mature
Classifier: Intended Audience :: Developers
Classifier: License :: OSI Approved :: Apache Software License
Classifier: Operating System :: MacOS :: MacOS X
Classifier: Operating System :: Microsoft :: Windows
Classifier: Operating System :: POSIX
Classifier: Programming Language :: Python
Classifier: Programming Language :: Python :: 3
Classifier: Topic :: Software Development :: Internationalization
Classifier: Topic :: Software Development :: Libraries
Classifier: Topic :: Software Development :: Libraries :: Python Modules
Classifier: Topic :: Software Development :: Localization
Requires-Python: >=3.9
Requires-Dist: atpublic
